{
  "1": {
    "revelationPlace": "ម៉ាក្កះ",
    "transliteratedName": "អាល់ហ្វាទីហះ",
    "versesCount": 7,
    "translatedName": "អ្នកបើក",
    "slug": "អាល់ហ្វាទីហះ"
  },
  "2": {
    "revelationPlace": "ម៉ាឌីណះ",
    "transliteratedName": "អាល់ហ្ពាក៏រ៉ោះ",
    "versesCount": 286,
    "translatedName": "គោ",
    "slug": "អាល់ហ្ពាក៏រ៉ោះ"
  },
  "3": {
    "revelationPlace": "ម៉ាឌីណះ",
    "transliteratedName": "អាលីអុិមរ៉ន",
    "versesCount": 200,
    "translatedName": "គ្រួសាររបស់ Imran",
    "slug": "អាលីអុិមរ៉ន"
  },
  "4": {
    "revelationPlace": "ម៉ាឌីណះ",
    "transliteratedName": "អាន់នីសាក",
    "versesCount": 176,
    "translatedName": "ស្ត្រី",
    "slug": "អាន់នីសាក"
  },
  "5": {
    "revelationPlace": "ម៉ាឌីណះ",
    "transliteratedName": "អាល់ម៉ាអ៊ីដះ",
    "versesCount": 120,
    "translatedName": "ការរីករាលដាលតារាង",
    "slug": "អាល់ម៉ាអ៊ីដះ"
  },
  "6": {
    "revelationPlace": "ម៉ាក្កះ",
    "transliteratedName": "អាល់អាន់អាម",
    "versesCount": 165,
    "translatedName": "គោក្របី",
    "slug": "អាល់អាន់អាម"
  },
  "7": {
    "revelationPlace": "ម៉ាក្កះ",
    "transliteratedName": "អាល់អាក់រ៉ហ្វ",
    "versesCount": 206,
    "translatedName": "កម្ពស់",
    "slug": "អាល់អាក់រ៉ហ្វ"
  },
  "8": {
    "revelationPlace": "ម៉ាឌីណះ",
    "transliteratedName": "អាល់អាន់ហ្វាល",
    "versesCount": 75,
    "translatedName": "The Spoils of War",
    "slug": "អាល់អាន់ហ្វាល"
  },
  "9": {
    "revelationPlace": "ម៉ាឌីណះ",
    "transliteratedName": "អាត់តាវហ្ពះ",
    "versesCount": 129,
    "translatedName": "ការប្រែចិត្ត",
    "slug": "អាត់តាវហ្ពះ"
  },
  "10": {
    "revelationPlace": "ម៉ាក្កះ",
    "transliteratedName": "យូនូស",
    "versesCount": 109,
    "translatedName": "យ៉ូណាស",
    "slug": "យូនូស"
  },
  "11": {
    "revelationPlace": "ម៉ាក្កះ",
    "transliteratedName": "ហ៊ូទ",
    "versesCount": 123,
    "translatedName": "ហ៊ូដ",
    "slug": "ហ៊ូទ"
  },
  "12": {
    "revelationPlace": "ម៉ាក្កះ",
    "transliteratedName": "យូសុហ្វ",
    "versesCount": 111,
    "translatedName": "យ៉ូសែប",
    "slug": "យូសុហ្វ"
  },
  "13": {
    "revelationPlace": "ម៉ាឌីណះ",
    "transliteratedName": "អើររ៉ក់ទ៍",
    "versesCount": 43,
    "translatedName": "ផ្គរលាន់",
    "slug": "អើររ៉ក់ទ៍"
  },
  "14": {
    "revelationPlace": "ម៉ាក្កះ",
    "transliteratedName": "អ៊ីព្រហ៊ីម",
    "versesCount": 52,
    "translatedName": "អ័ប្រាហាំ",
    "slug": "អ៊ីព្រហ៊ីម"
  },
  "15": {
    "revelationPlace": "ម៉ាក្កះ",
    "transliteratedName": "អាល់ហុិជរ៍",
    "versesCount": 99,
    "translatedName": "ផ្លូវថ្ម",
    "slug": "អាល់ហុិជរ៍"
  },
  "16": {
    "revelationPlace": "ម៉ាក្កះ",
    "transliteratedName": "អាន់ណះល៍",
    "versesCount": 128,
    "translatedName": "សត្វឃ្មុំ",
    "slug": "អាន់ណះល៍"
  },
  "17": {
    "revelationPlace": "ម៉ាក្កះ",
    "transliteratedName": "អាល់អ៊ីសរ៉ក",
    "versesCount": 111,
    "translatedName": "ដំណើររាត្រី",
    "slug": "អាល់អ៊ីសរ៉ក"
  },
  "18": {
    "revelationPlace": "ម៉ាក្កះ",
    "transliteratedName": "អាល់កះហ្វុី",
    "versesCount": 110,
    "translatedName": "គុហា",
    "slug": "អាល់កះហ្វុី"
  },
  "19": {
    "revelationPlace": "ម៉ាក្កះ",
    "transliteratedName": "ម៉ារយុាំ",
    "versesCount": 98,
    "translatedName": "ម៉ារី",
    "slug": "ម៉ារយុាំ"
  },
  "20": {
    "revelationPlace": "ម៉ាក្កះ",
    "transliteratedName": "តាហា",
    "versesCount": 135,
    "translatedName": "តាហា",
    "slug": "តាហា"
  },
  "21": {
    "revelationPlace": "ម៉ាក្កះ",
    "transliteratedName": "អាល់អាំពីយ៉ាក",
    "versesCount": 112,
    "translatedName": "ហោរា",
    "slug": "អាល់អាំពីយ៉ាក"
  },
  "22": {
    "revelationPlace": "ម៉ាឌីណះ",
    "transliteratedName": "អាល់ហាជ្ជ",
    "versesCount": 78,
    "translatedName": "ធម្មយាត្រា",
    "slug": "អាល់ហាជ្ជ"
  },
  "23": {
    "revelationPlace": "ម៉ាក្កះ",
    "transliteratedName": "អាល់មូមីនូន",
    "versesCount": 118,
    "translatedName": "អ្នកជឿ",
    "slug": "អាល់មូមីនូន"
  },
  "24": {
    "revelationPlace": "ម៉ាឌីណះ",
    "transliteratedName": "អាន់នូរ",
    "versesCount": 64,
    "translatedName": "ពន្លឺ",
    "slug": "អាន់នូរ"
  },
  "25": {
    "revelationPlace": "ម៉ាក្កះ",
    "transliteratedName": "អាល់ហ្វូរកន",
    "versesCount": 77,
    "translatedName": "លក្ខណៈវិនិច្ឆ័យ",
    "slug": "អាល់ហ្វូរកន"
  },
  "26": {
    "revelationPlace": "ម៉ាក្កះ",
    "transliteratedName": "អាស្ហស្ហ៊ូអារ៉ក",
    "versesCount": 227,
    "translatedName": "កវី",
    "slug": "អាស្ហស្ហ៊ូអារ៉ក"
  },
  "27": {
    "revelationPlace": "ម៉ាក្កះ",
    "transliteratedName": "អាន់ណាំល៍",
    "versesCount": 93,
    "translatedName": "ស្រមោច",
    "slug": "អាន់ណាំល៍"
  },
  "28": {
    "revelationPlace": "ម៉ាក្កះ",
    "transliteratedName": "អាល់កសស",
    "versesCount": 88,
    "translatedName": "រឿង",
    "slug": "អាល់កសស"
  },
  "29": {
    "revelationPlace": "ម៉ាក្កះ",
    "transliteratedName": "អាល់អាំងកាពូត",
    "versesCount": 69,
    "translatedName": "សត្វពីងពាង",
    "slug": "អាល់អាំងកាពូត"
  },
  "30": {
    "revelationPlace": "ម៉ាក្កះ",
    "transliteratedName": "អើររ៉ូម",
    "versesCount": 60,
    "translatedName": "ជនជាតិរ៉ូម",
    "slug": "អើររ៉ូម"
  },
  "31": {
    "revelationPlace": "ម៉ាក្កះ",
    "transliteratedName": "លុកម៉ាន",
    "versesCount": 34,
    "translatedName": "Luqman",
    "slug": "លុកម៉ាន"
  },
  "32": {
    "revelationPlace": "ម៉ាក្កះ",
    "transliteratedName": "អាស់សាជដះ",
    "versesCount": 30,
    "translatedName": "ការថ្វាយបង្គំ",
    "slug": "អាស់សាជដះ"
  },
  "33": {
    "revelationPlace": "ម៉ាឌីណះ",
    "transliteratedName": "អាល់អះហ្សាប",
    "versesCount": 73,
    "translatedName": "កងកម្លាំងចម្រុះ",
    "slug": "អាល់អះហ្សាប"
  },
  "34": {
    "revelationPlace": "ម៉ាក្កះ",
    "transliteratedName": "សាហ្ពាក",
    "versesCount": 54,
    "translatedName": "សេបា",
    "slug": "សាហ្ពាក"
  },
  "35": {
    "revelationPlace": "ម៉ាក្កះ",
    "transliteratedName": "ហ្វាតៀរ",
    "versesCount": 45,
    "translatedName": "អ្នកបង្កើត",
    "slug": "ហ្វាតៀរ"
  },
  "36": {
    "revelationPlace": "ម៉ាក្កះ",
    "transliteratedName": "យ៉ាស៊ីន",
    "versesCount": 83,
    "translatedName": "យ៉ាស៊ិន",
    "slug": "យ៉ាសុីន"
  },
  "37": {
    "revelationPlace": "ម៉ាក្កះ",
    "transliteratedName": "អាស់សហ្វហ្វាត",
    "versesCount": 182,
    "translatedName": "អ្នកដែលកំណត់ចំណាត់ថ្នាក់",
    "slug": "អាស់សហ្វហ្វាត"
  },
  "38": {
    "revelationPlace": "ម៉ាក្កះ",
    "transliteratedName": "សទ",
    "versesCount": 88,
    "translatedName": "សំបុត្រ \"សាដ\"",
    "slug": "សទ"
  },
  "39": {
    "revelationPlace": "ម៉ាក្កះ",
    "transliteratedName": "អាស់ហ្សូមើរ",
    "versesCount": 75,
    "translatedName": "កងទ័ព",
    "slug": "អាស់ហ្សូមើរ"
  },
  "40": {
    "revelationPlace": "ម៉ាក្កះ",
    "transliteratedName": "ហ្គាហ្វៀរ",
    "versesCount": 85,
    "translatedName": "អ្នកអភ័យទោស",
    "slug": "ហ្គាហ្វៀរ"
  },
  "41": {
    "revelationPlace": "ម៉ាក្កះ",
    "transliteratedName": "ហ្វូសស៊ីឡាត់",
    "versesCount": 54,
    "translatedName": "ពន្យល់លម្អិត",
    "slug": "ហ្វូសស៊ីឡាត់"
  },
  "42": {
    "revelationPlace": "ម៉ាក្កះ",
    "transliteratedName": "អាស្ហ់ស្ហ៊ូរ៉",
    "versesCount": 53,
    "translatedName": "ការពិគ្រោះយោបល់",
    "slug": "អាស្ហ់ស្ហ៊ូរ៉"
  },
  "43": {
    "revelationPlace": "ម៉ាក្កះ",
    "transliteratedName": "អាហ្សហ្សុខរ៉ហ្វ",
    "versesCount": 89,
    "translatedName": "គ្រឿងអលង្ការមាស",
    "slug": "អាហ្សហ្សុខរ៉ហ្វ"
  },
  "44": {
    "revelationPlace": "ម៉ាក្កះ",
    "transliteratedName": "អាអាត់ទូខន",
    "versesCount": 59,
    "translatedName": "ផ្សែង",
    "slug": "អាត់ទូខន"
  },
  "45": {
    "revelationPlace": "ម៉ាក្កះ",
    "transliteratedName": "អាល់ហ្ជាស៊ីយ៉ះ",
    "versesCount": 37,
    "translatedName": "The Crouching",
    "slug": "អាល់ហ្ជាស៊ីយ៉ះ"
  },
  "46": {
    "revelationPlace": "ម៉ាក្កះ",
    "transliteratedName": "អាល់អះកហ្វ",
    "versesCount": 35,
    "translatedName": "វាលខ្សាច់កោងខ្យល់",
    "slug": "អាល់អះកហ្វ"
  },
  "47": {
    "revelationPlace": "ម៉ាឌីណះ",
    "transliteratedName": "មូហាំម៉ាត់",
    "versesCount": 38,
    "translatedName": "លោក Muhammad",
    "slug": "មូហាំម៉ាត់"
  },
  "48": {
    "revelationPlace": "ម៉ាឌីណះ",
    "transliteratedName": "អាល់ហ្វាត់ហ៍",
    "versesCount": 29,
    "translatedName": "ជ័យជំនះ",
    "slug": "អាល់ហ្វាត់ហ៍"
  },
  "49": {
    "revelationPlace": "ម៉ាឌីណះ",
    "transliteratedName": "អាល់ហ៊ូជូរ៉ត",
    "versesCount": 18,
    "translatedName": "បន្ទប់",
    "slug": "អាល់ហ៊ូជូរ៉ត"
  },
  "50": {
    "revelationPlace": "ម៉ាក្កះ",
    "transliteratedName": "កហ្វ",
    "versesCount": 45,
    "translatedName": "លិខិត \"កាហ្វ\"",
    "slug": "កហ្វ"
  },
  "51": {
    "revelationPlace": "ម៉ាក្កះ",
    "transliteratedName": "អាស់ហ្សារីយ៉ាត",
    "versesCount": 60,
    "translatedName": "ខ្យល់ Winnowing",
    "slug": "អាស់ហ្សារីយ៉ាត"
  },
  "52": {
    "revelationPlace": "ម៉ាក្កះ",
    "transliteratedName": "អាត់តួរ",
    "versesCount": 49,
    "translatedName": "ភ្នំ",
    "slug": "អាត់តួរ"
  },
  "53": {
    "revelationPlace": "ម៉ាក្កះ",
    "transliteratedName": "អាន់ណាច់ម៍",
    "versesCount": 62,
    "translatedName": "តារា",
    "slug": "អាន់ណាច់ម៍"
  },
  "54": {
    "revelationPlace": "ម៉ាក្កះ",
    "transliteratedName": "អាល់កមើរ",
    "versesCount": 55,
    "translatedName": "ព្រះច័ន្ទ",
    "slug": "អាល់កមើរ"
  },
  "55": {
    "revelationPlace": "ម៉ាឌីណះ",
    "transliteratedName": "អើររ៉ោះម៉ាន",
    "versesCount": 78,
    "translatedName": "អ្នកមានគុណ",
    "slug": "អើររ៉ោះម៉ាន"
  },
  "56": {
    "revelationPlace": "ម៉ាក្កះ",
    "transliteratedName": "អាល់វ៉ាគីអះ",
    "versesCount": 96,
    "translatedName": "ជៀសមិនរួច",
    "slug": "អាល់វ៉ាគីអះ"
  },
  "57": {
    "revelationPlace": "ម៉ាឌីណះ",
    "transliteratedName": "អាល់ហាទីត",
    "versesCount": 29,
    "translatedName": "ដែក",
    "slug": "អាល់ហាទីត"
  },
  "58": {
    "revelationPlace": "ម៉ាឌីណះ",
    "transliteratedName": "អាលមូជើទើឡះ",
    "versesCount": 22,
    "translatedName": "ស្ត្រីអង្វរ",
    "slug": "អាលមូជើទើឡះ"
  },
  "59": {
    "revelationPlace": "ម៉ាឌីណះ",
    "transliteratedName": "អាល់ហាស្ហរ៍",
    "versesCount": 24,
    "translatedName": "និរទេសខ្លួន",
    "slug": "អាល់ហាស្ហរ៍"
  },
  "60": {
    "revelationPlace": "ម៉ាឌីណះ",
    "transliteratedName": "អាល់មុមតាហុីណះ",
    "versesCount": 13,
    "translatedName": "នាងដែលត្រូវពិនិត្យ",
    "slug": "អាល់មុមតាហុីណះ"
  },
  "61": {
    "revelationPlace": "ម៉ាឌីណះ",
    "transliteratedName": "អាសសហ្វ",
    "versesCount": 14,
    "translatedName": "ចំណាត់ថ្នាក់",
    "slug": "អាសសហ្វ"
  },
  "62": {
    "revelationPlace": "ម៉ាឌីណះ",
    "transliteratedName": "ជូមូអះ",
    "versesCount": 11,
    "translatedName": "ក្រុមជំនុំ, ថ្ងៃសុក្រ",
    "slug": "ជូមូអះ"
  },
  "63": {
    "revelationPlace": "ម៉ាឌីណះ",
    "transliteratedName": "អាល់មូណាហ្វុីគូន",
    "versesCount": 11,
    "translatedName": "ពួកពុតត្បុត",
    "slug": "អាល់មូណាហ្វុីគូន"
  },
  "64": {
    "revelationPlace": "ម៉ាឌីណះ",
    "transliteratedName": "អាត់តាហ្គពុន",
    "versesCount": 18,
    "translatedName": "ការមិនសប្បាយចិត្តទៅវិញទៅមក",
    "slug": "អាត់តាហ្គពុន"
  },
  "65": {
    "revelationPlace": "ម៉ាឌីណះ",
    "transliteratedName": "អាត់តឡាគ",
    "versesCount": 12,
    "translatedName": "ការលែងលះ",
    "slug": "អាត់តឡាគ"
  },
  "66": {
    "revelationPlace": "ម៉ាឌីណះ",
    "transliteratedName": "អាត់តះរីម",
    "versesCount": 12,
    "translatedName": "ការហាមឃាត់",
    "slug": "អាត់តះរីម"
  },
  "67": {
    "revelationPlace": "ម៉ាក្កះ",
    "transliteratedName": "អាល់មុលក៍",
    "versesCount": 30,
    "translatedName": "អធិបតេយ្យភាព",
    "slug": "អាល់មុលក៍"
  },
  "68": {
    "revelationPlace": "ម៉ាក្កះ",
    "transliteratedName": "អាល់កឡាំ",
    "versesCount": 52,
    "translatedName": "ប៊ិច",
    "slug": "អាល់កឡាំ"
  },
  "69": {
    "revelationPlace": "ម៉ាក្កះ",
    "transliteratedName": "អាល់ហាគកោះ",
    "versesCount": 52,
    "translatedName": "ការពិត",
    "slug": "អាល់ហាគកោះ"
  },
  "70": {
    "revelationPlace": "ម៉ាក្កះ",
    "transliteratedName": "អាល់ម៉ាអារិច",
    "versesCount": 44,
    "translatedName": "ជណ្តើរឡើង",
    "slug": "អាល់ម៉ាអារិច"
  },
  "71": {
    "revelationPlace": "ម៉ាក្កះ",
    "transliteratedName": "នួហ",
    "versesCount": 28,
    "translatedName": "ណូអេ",
    "slug": "នួហ"
  },
  "72": {
    "revelationPlace": "ម៉ាក្កះ",
    "transliteratedName": "អាល់ជិន",
    "versesCount": 28,
    "translatedName": "ជិន",
    "slug": "អាល់ជិន"
  },
  "73": {
    "revelationPlace": "ម៉ាក្កះ",
    "transliteratedName": "អាល់មូសហ្សាំមិល",
    "versesCount": 20,
    "translatedName": "The Enshrouded One",
    "slug": "អាល់មូសហ្សាំមិល"
  },
  "74": {
    "revelationPlace": "ម៉ាក្កះ",
    "transliteratedName": "អាល់មុដដាស់សៀរ",
    "versesCount": 56,
    "translatedName": "The Cloaked One",
    "slug": "អាល់មុដដាស់សៀរ"
  },
  "75": {
    "revelationPlace": "ម៉ាក្កះ",
    "transliteratedName": "អាល់គីយ៉ាម៉ះ",
    "versesCount": 40,
    "translatedName": "ការរស់ឡើងវិញ",
    "slug": "អាល់គីយ៉ាម៉ះ"
  },
  "76": {
    "revelationPlace": "ម៉ាឌីណះ",
    "transliteratedName": "អាល់អ៊ីនសាន",
    "versesCount": 31,
    "translatedName": "បុរស",
    "slug": "អាល់អ៊ីនសាន"
  },
  "77": {
    "revelationPlace": "ម៉ាក្កះ",
    "transliteratedName": "អាល់មូរសុីឡាត",
    "versesCount": 50,
    "translatedName": "អ្នកតំណាង",
    "slug": "អាល់មូរសុីឡាត"
  },
  "78": {
    "revelationPlace": "ម៉ាក្កះ",
    "transliteratedName": "អាន់ណាហ្ពាក",
    "versesCount": 40,
    "translatedName": "ដំណឹង",
    "slug": "អាន់ណាហ្ពាក"
  },
  "79": {
    "revelationPlace": "ម៉ាក្កះ",
    "transliteratedName": "អាន់ណាហ្សុីអាត",
    "versesCount": 46,
    "translatedName": "អ្នកដែលអូសទៅមុខ",
    "slug": "អាន់ណាហ្សុីអាត"
  },
  "80": {
    "revelationPlace": "ម៉ាក្កះ",
    "transliteratedName": "'អាហ្ពាសា",
    "versesCount": 42,
    "translatedName": "គាត់បានព្រិចភ្នែក",
    "slug": "អាហ្ពាសា"
  },
  "81": {
    "revelationPlace": "ម៉ាក្កះ",
    "transliteratedName": "អាត់តឹកវៀរ",
    "versesCount": 29,
    "translatedName": "ការផ្តួលរំលំ",
    "slug": "អាត់តឹកវៀរ"
  },
  "82": {
    "revelationPlace": "ម៉ាក្កះ",
    "transliteratedName": "អាល់អ៊ីមហ្វុីត័រ",
    "versesCount": 19,
    "translatedName": "ការបោសសំអាត",
    "slug": "អាល់អ៊ីមហ្វុីត័រ"
  },
  "83": {
    "revelationPlace": "ម៉ាក្កះ",
    "transliteratedName": "អាល់មូតហ្វហ្វុីហ្វុីន",
    "versesCount": 36,
    "translatedName": "ការក្លែងបន្លំ",
    "slug": "អាល់មូតហ្វហ្វុីហ្វុីន"
  },
  "84": {
    "revelationPlace": "ម៉ាក្កះ",
    "transliteratedName": "អាល់អុិនស្ហុីកក",
    "versesCount": 25,
    "translatedName": "The Sundering",
    "slug": "អាល់អុិនស្ហុីកក"
  },
  "85": {
    "revelationPlace": "ម៉ាក្កះ",
    "transliteratedName": "អាល់ពូរូជ",
    "versesCount": 22,
    "translatedName": "វិមាននៃផ្កាយ",
    "slug": "អាល់ពូរូជ"
  },
  "86": {
    "revelationPlace": "ម៉ាក្កះ",
    "transliteratedName": "អាត់តរិក",
    "versesCount": 17,
    "translatedName": "អ្នករាត្រី",
    "slug": "អាត់តរិក"
  },
  "87": {
    "revelationPlace": "ម៉ាក្កះ",
    "transliteratedName": "អាល់អាក់ឡា",
    "versesCount": 19,
    "translatedName": "ខ្ពស់បំផុត",
    "slug": "អាល់អាក់ឡា"
  },
  "88": {
    "revelationPlace": "ម៉ាក្កះ",
    "transliteratedName": "អាល់ហ្គស្ហុីយ៉ះ",
    "versesCount": 26,
    "translatedName": "លើសលប់",
    "slug": "អាល់ហ្គស្ហុីយ៉ះ"
  },
  "89": {
    "revelationPlace": "ម៉ាក្កះ",
    "transliteratedName": "អាល់ហ្វាច់រ៍",
    "versesCount": 30,
    "translatedName": "ព្រឹកព្រលឹម",
    "slug": "អាល់ហ្វាច់រ៍"
  },
  "90": {
    "revelationPlace": "ម៉ាក្កះ",
    "transliteratedName": "អាល់ហ្ពាឡាត់",
    "versesCount": 20,
    "translatedName": "ទីក្រុង",
    "slug": "អាល់ហ្ពាឡាត់"
  },
  "91": {
    "revelationPlace": "ម៉ាក្កះ",
    "transliteratedName": "អាស់ស្ហាំ",
    "versesCount": 15,
    "translatedName": "ព្រះអាទិត្យ",
    "slug": "អាស់ស្ហាំ"
  },
  "92": {
    "revelationPlace": "ម៉ាក្កះ",
    "transliteratedName": "អាល់ឡៃល៍",
    "versesCount": 21,
    "translatedName": "រាត្រី",
    "slug": "អាល់ឡៃល៍"
  },
  "93": {
    "revelationPlace": "ម៉ាក្កះ",
    "transliteratedName": "អាត់ទូហា",
    "versesCount": 11,
    "translatedName": "ម៉ោងពេលព្រឹក",
    "slug": "អាត់ទូហា"
  },
  "94": {
    "revelationPlace": "ម៉ាក្កះ",
    "transliteratedName": "អាស្ហស្ហើរហ៍",
    "versesCount": 8,
    "translatedName": "ការសង្គ្រោះ",
    "slug": "អាស្ហស្ហើរហ៍"
  },
  "95": {
    "revelationPlace": "ម៉ាក្កះ",
    "transliteratedName": "អាត់ទីន",
    "versesCount": 8,
    "translatedName": "រូបភព",
    "slug": "អាត់ទីន"
  },
  "96": {
    "revelationPlace": "ម៉ាក្កះ",
    "transliteratedName": "អាល់អាឡឹក",
    "versesCount": 19,
    "translatedName": "ក្លូត",
    "slug": "អាល់អាឡឹក"
  },
  "97": {
    "revelationPlace": "ម៉ាក្កះ",
    "transliteratedName": "អាល់កដរ៍",
    "versesCount": 5,
    "translatedName": "អំណាច",
    "slug": "អាល់កដរ៍"
  },
  "98": {
    "revelationPlace": "ម៉ាឌីណះ",
    "transliteratedName": "អាល់ហ្ពៃយីណះ",
    "versesCount": 8,
    "translatedName": "ភស្តុតាងច្បាស់លាស់",
    "slug": "អាល់ហ្ពៃយីណះ"
  },
  "99": {
    "revelationPlace": "ម៉ាឌីណះ",
    "transliteratedName": "អាល់ហ្សាល់ហ្សាឡះ",
    "versesCount": 8,
    "translatedName": "ការរញ្ជួយដី",
    "slug": "អាល់ហ្សាល់ហ្សាឡះ"
  },
  "100": {
    "revelationPlace": "ម៉ាក្កះ",
    "transliteratedName": "អាល់អាទីយ៉ាត",
    "versesCount": 11,
    "translatedName": "អ្នកបង្ហាត់បង្រៀន",
    "slug": "អាល់អាទីយ៉ាត"
  },
  "101": {
    "revelationPlace": "ម៉ាក្កះ",
    "transliteratedName": "អាល់ករីអះ",
    "versesCount": 11,
    "translatedName": "គ្រោះមហន្តរាយ",
    "slug": "អាល់ករីអះ"
  },
  "102": {
    "revelationPlace": "ម៉ាក្កះ",
    "transliteratedName": "អាត់តាកាស៊ួរ",
    "versesCount": 8,
    "translatedName": "ការប្រកួតប្រជែងក្នុងពិភពលោកកើនឡើង",
    "slug": "អាត់តាកាស៊ួរ"
  },
  "103": {
    "revelationPlace": "ម៉ាក្កះ",
    "transliteratedName": "អាល់អោសរ៍",
    "versesCount": 3,
    "translatedName": "ថ្ងៃធ្លាក់ចុះ",
    "slug": "អាល់អោសរ៍"
  },
  "104": {
    "revelationPlace": "ម៉ាក្កះ",
    "transliteratedName": "អាល់ហ៊ូម៉ាហ្សះ",
    "versesCount": 9,
    "translatedName": "ពាណិជ្ជករ",
    "slug": "អាល់ហ៊ូម៉ាហ្សះ"
  },
  "105": {
    "revelationPlace": "ម៉ាក្កះ",
    "transliteratedName": "អាល់ហ្វុីល",
    "versesCount": 5,
    "translatedName": "ដំរី",
    "slug": "អាល់ហ្វុីល"
  },
  "106": {
    "revelationPlace": "ម៉ាក្កះ",
    "transliteratedName": "អាល់គូរ៉ស្ហ",
    "versesCount": 4,
    "translatedName": "Quraysh",
    "slug": "អាល់គូរ៉ស្ហ"
  },
  "107": {
    "revelationPlace": "ម៉ាក្កះ",
    "transliteratedName": "អាល់ម៉ាអូន",
    "versesCount": 7,
    "translatedName": "សេចក្តីសប្បុរសតូចតាច",
    "slug": "អាល់ម៉ាអូន"
  },
  "108": {
    "revelationPlace": "ម៉ាក្កះ",
    "transliteratedName": "អាល់កាវសើរ",
    "versesCount": 3,
    "translatedName": "បរិបូរណ៍",
    "slug": "អាល់កាវសើរ"
  },
  "109": {
    "revelationPlace": "ម៉ាក្កះ",
    "transliteratedName": "អាល់កាហ្វីរូន",
    "versesCount": 6,
    "translatedName": "អ្នកមិនជឿ",
    "slug": "អាល់កាហ្វីរូន"
  },
  "110": {
    "revelationPlace": "ម៉ាឌីណះ",
    "transliteratedName": "អាន់ណើសរ៍",
    "versesCount": 3,
    "translatedName": "ជំនួយដ៏ទេវភាព",
    "slug": "អាន់ណើសរ៍"
  },
  "111": {
    "revelationPlace": "ម៉ាក្កះ",
    "transliteratedName": "អាល់ម៉ាសាដ",
    "versesCount": 5,
    "translatedName": "សរសៃដូង",
    "slug": "អាល់ម៉ាសាដ"
  },
  "112": {
    "revelationPlace": "ម៉ាក្កះ",
    "transliteratedName": "អាល់អៀខឡោស",
    "versesCount": 4,
    "translatedName": "ភាពស្មោះត្រង់",
    "slug": "អាល់អៀខឡោស"
  },
  "113": {
    "revelationPlace": "ម៉ាក្កះ",
    "transliteratedName": "អាល់ហ្វាឡឹក",
    "versesCount": 5,
    "translatedName": "ថ្ងៃរះ",
    "slug": "អាល់ហ្វាឡឹក"
  },
  "114": {
    "revelationPlace": "ម៉ាក្កះ",
    "transliteratedName": "អាន់ណាស",
    "versesCount": 6,
    "translatedName": "មនុស្សជាតិ",
    "slug": "អាន់ណាស"
  }
}
